vector_search_api/__init__.py
vector_search_api/config.py
vector_search_api/exceptions/__init__.py
vector_search_api/exceptions/search.py
vector_search_api/helper/__init__.py
vector_search_api/helper/utils.py
vector_search_api/helper/vector.py
vector_search_api/schema/__init__.py
vector_search_api/schema/base.py
vector_search_api/schema/result.py
vector_search_api/search/__init__.py
vector_search_api/search/base_vector_search.py
vector_search_api/search/faiss_vector_search.py
vector_search_api/search/in_memory_vector_search.py
vector_search_api/search/pinecone_vector_search.py
vector_search_api/version.py
vector_search_api-0.4.2.dist-info/LICENSE
vector_search_api-0.4.2.dist-info/WHEEL
vector_search_api-0.4.2.dist-info/METADATA
vector_search_api-0.4.2.dist-info/RECORD
