Metadata-Version: 2.1
Name: vector-search-api
Version: 0.4.2
Summary: Vector-Search API of databases.
License: MIT
Author: AllenChou
Author-email: f1470891079@gmail.com
Requires-Python: >=3.7.1,<4.0.0
Classifier: License :: OSI Approved :: MIT License
Classifier: Programming Language :: Python :: 3
Classifier: Programming Language :: Python :: 3.8
Classifier: Programming Language :: Python :: 3.9
Classifier: Programming Language :: Python :: 3.10
Classifier: Programming Language :: Python :: 3.11
Provides-Extra: all
Provides-Extra: faiss
Provides-Extra: pinecone
Requires-Dist: faiss-cpu (>=1.0.0,<2.0.0); extra == "all" or extra == "faiss"
Requires-Dist: numpy (>=1.0.0,<2.0.0)
Requires-Dist: pinecone-client (>=2.0.0,<3.0.0); extra == "all" or extra == "pinecone"
